{"name":"Sadaf 2","area":"Marsa Dubai","proj":"","sn":314,"rn":0,"sy":[{"y":2008,"n":99,"rd":99,"ppsqm":5720,"price":1560000,"rd_ppsqm":5720},{"y":2009,"n":25,"rd":25,"ppsqm":5541,"price":1210000,"rd_ppsqm":5541},{"y":2010,"n":15,"rd":15,"ppsqm":8461,"price":1100000,"rd_ppsqm":8461},{"y":2011,"n":7,"rd":7,"ppsqm":8464,"price":1250000,"rd_ppsqm":8464},{"y":2012,"n":22,"rd":22,"ppsqm":8332,"price":1725000,"rd_ppsqm":8332},{"y":2013,"n":17,"rd":17,"ppsqm":10533,"price":1990000,"rd_ppsqm":10533},{"y":2014,"n":15,"rd":15,"ppsqm":14475,"price":2300000,"rd_ppsqm":14475},{"y":2015,"n":17,"rd":17,"ppsqm":12413,"price":2550000,"rd_ppsqm":12413},{"y":2016,"n":10,"rd":10,"ppsqm":12723,"price":1900000,"rd_ppsqm":12723},{"y":2017,"n":8,"rd":8,"ppsqm":12600,"price":2225000,"rd_ppsqm":12600},{"y":2018,"n":6,"rd":6,"ppsqm":11178,"price":1775000,"rd_ppsqm":11178},{"y":2019,"n":4,"rd":4,"ppsqm":8910,"price":1630000,"rd_ppsqm":8910},{"y":2020,"n":7,"rd":7,"ppsqm":6869,"price":1220000,"rd_ppsqm":6869},{"y":2021,"n":10,"rd":10,"ppsqm":10199,"price":1817500,"rd_ppsqm":10199},{"y":2022,"n":9,"rd":9,"ppsqm":10985,"price":2200000,"rd_ppsqm":10985},{"y":2023,"n":17,"rd":17,"ppsqm":12444,"price":2040000,"rd_ppsqm":12444},{"y":2024,"n":15,"rd":15,"ppsqm":14080,"price":2600000,"rd_ppsqm":14080},{"y":2025,"n":8,"rd":8,"ppsqm":15031,"price":2950000,"rd_ppsqm":15031},{"y":2026,"n":3,"rd":3,"ppsqm":14230,"price":2200000,"rd_ppsqm":14230}],"sr":{"2br":[{"y":2008,"n":26,"ppsqm":5800,"price":750000},{"y":2009,"n":7,"ppsqm":4603,"price":599000},{"y":2010,"n":5,"ppsqm":5584,"price":720000},{"y":2011,"n":5,"ppsqm":9643,"price":1500000},{"y":2012,"n":2,"ppsqm":7357,"price":950000},{"y":2013,"n":4,"ppsqm":13923,"price":1800000},{"y":2014,"n":5,"ppsqm":17390,"price":2240000},{"y":2015,"n":6,"ppsqm":12554,"price":1212000},{"y":2016,"n":5,"ppsqm":13448,"price":1750000},{"y":2017,"n":2,"ppsqm":12798,"price":1650000},{"y":2018,"n":3,"ppsqm":12266,"price":1580000},{"y":2021,"n":4,"ppsqm":10800,"price":1390000},{"y":2023,"n":8,"ppsqm":13610,"price":1750000},{"y":2024,"n":4,"ppsqm":14203,"price":2051024},{"y":2025,"n":2,"ppsqm":15229,"price":1981772},{"y":2026,"n":2,"ppsqm":14989,"price":1936205}],"3br":[{"y":2008,"n":36,"ppsqm":4008,"price":699000},{"y":2009,"n":10,"ppsqm":7278,"price":1280000},{"y":2010,"n":7,"ppsqm":3996,"price":699000},{"y":2011,"n":1,"ppsqm":6711,"price":1200000},{"y":2012,"n":8,"ppsqm":4807,"price":850000},{"y":2013,"n":5,"ppsqm":4008,"price":699000},{"y":2014,"n":7,"ppsqm":14291,"price":2500000},{"y":2015,"n":2,"ppsqm":15203,"price":2681838},{"y":2016,"n":2,"ppsqm":11779,"price":2075000},{"y":2017,"n":5,"ppsqm":12757,"price":2225000},{"y":2018,"n":2,"ppsqm":10943,"price":1925000},{"y":2019,"n":2,"ppsqm":8910,"price":1561626},{"y":2020,"n":4,"ppsqm":6657,"price":1162808},{"y":2021,"n":1,"ppsqm":11094,"price":1935000},{"y":2022,"n":6,"ppsqm":11084,"price":1960000},{"y":2023,"n":4,"ppsqm":11423,"price":2020000},{"y":2024,"n":4,"ppsqm":13899,"price":2457500},{"y":2025,"n":3,"ppsqm":15327,"price":2700000},{"y":2026,"n":1,"ppsqm":14230,"price":2500000}],"4br+":[{"y":2008,"n":36,"ppsqm":8852,"price":2550000},{"y":2009,"n":8,"ppsqm":6896,"price":1980000},{"y":2010,"n":3,"ppsqm":9160,"price":2650000},{"y":2011,"n":1,"ppsqm":3280,"price":949000},{"y":2012,"n":6,"ppsqm":8471,"price":2175000},{"y":2013,"n":7,"ppsqm":10369,"price":3000000},{"y":2014,"n":2,"ppsqm":8658,"price":2876500},{"y":2015,"n":9,"ppsqm":11441,"price":3200000},{"y":2016,"n":2,"ppsqm":12165,"price":3575000},{"y":2017,"n":1,"ppsqm":11902,"price":3050000},{"y":2018,"n":1,"ppsqm":10237,"price":3400000},{"y":2019,"n":2,"ppsqm":7226,"price":2030000},{"y":2020,"n":2,"ppsqm":7561,"price":2245000},{"y":2021,"n":5,"ppsqm":8194,"price":2350000},{"y":2022,"n":3,"ppsqm":10633,"price":2940000},{"y":2023,"n":4,"ppsqm":11868,"price":3112500},{"y":2024,"n":5,"ppsqm":13247,"price":4400000},{"y":2025,"n":2,"ppsqm":13655,"price":3725000}],"other":[{"y":2008,"n":1,"ppsqm":11774,"price":2685000},{"y":2012,"n":6,"ppsqm":9044,"price":5250000},{"y":2013,"n":1,"ppsqm":11080,"price":2260000},{"y":2014,"n":1,"ppsqm":20544,"price":4000000},{"y":2016,"n":1,"ppsqm":15474,"price":2620000},{"y":2020,"n":1,"ppsqm":9647,"price":2200000},{"y":2023,"n":1,"ppsqm":11733,"price":6750000},{"y":2024,"n":2,"ppsqm":14718,"price":5350000},{"y":2025,"n":1,"ppsqm":17463,"price":3400000}]},"ry":[],"rr":{}}