{"name":"RR RESIDENCE","area":"Madinat Al Mataar","proj":"","sn":80,"rn":0,"sy":[{"y":2025,"n":14,"rd":14,"ppsqm":12568,"price":745000,"rd_ppsqm":12568},{"y":2026,"n":66,"rd":66,"ppsqm":12950,"price":781436,"rd_ppsqm":12950}],"sr":{"studio":[{"y":2026,"n":2,"ppsqm":14589,"price":314550,"rd_n":2,"rd_ppsqm":14589}],"1br":[{"y":2025,"n":13,"ppsqm":12406,"price":740000,"rd_n":13,"rd_ppsqm":12406},{"y":2026,"n":25,"ppsqm":12822,"price":779728,"rd_n":25,"rd_ppsqm":12822}],"2br":[{"y":2025,"n":1,"ppsqm":12914,"price":1050000,"rd_n":1,"rd_ppsqm":12914},{"y":2026,"n":39,"ppsqm":13268,"price":950400,"rd_n":39,"rd_ppsqm":13268}]},"ry":[],"rr":{},"txs":[{"d":"2026-07-06","p":1470677,"sqm":105.1,"r":"2br","op":0},{"d":"2026-07-06","p":1475708,"sqm":105.5,"r":"2br","op":0},{"d":"2026-07-06","p":1472354,"sqm":105.2,"r":"2br","op":0},{"d":"2026-07-06","p":861692,"sqm":61.6,"r":"1br","op":0},{"d":"2026-07-06","p":1224392,"sqm":87.5,"r":"2br","op":0},{"d":"2026-07-06","p":1274767,"sqm":91.1,"r":"2br","op":0},{"d":"2026-07-06","p":1519089,"sqm":108.1,"r":"2br","op":0},{"d":"2026-06-23","p":810000,"sqm":61.5,"r":"1br","op":0},{"d":"2026-06-18","p":800000,"sqm":65.7,"r":"1br","op":0},{"d":"2026-06-12","p":360000,"sqm":25.1,"r":"1br","op":0},{"d":"2026-05-25","p":1377948,"sqm":106.7,"r":"2br","op":0},{"d":"2026-05-25","p":1377948,"sqm":106.9,"r":"2br","op":0},{"d":"2026-05-25","p":1388928,"sqm":107.5,"r":"2br","op":0},{"d":"2026-05-25","p":1389080,"sqm":108.8,"r":"2br","op":0},{"d":"2026-05-25","p":1397592,"sqm":108.2,"r":"2br","op":0},{"d":"2026-05-22","p":1000000,"sqm":105.2,"r":"2br","op":0},{"d":"2026-05-22","p":570648,"sqm":43.8,"r":"2br","op":0},{"d":"2026-05-08","p":1164900,"sqm":90.8,"r":"2br","op":0},{"d":"2026-05-05","p":438000,"sqm":31.5,"r":"2br","op":0},{"d":"2026-04-27","p":825000,"sqm":63.8,"r":"1br","op":0},{"d":"2026-04-20","p":429683,"sqm":31.7,"r":"2br","op":0},{"d":"2026-04-20","p":444666,"sqm":32.5,"r":"2br","op":0},{"d":"2026-04-17","p":442238,"sqm":77.2,"r":"2br","op":0},{"d":"2026-04-16","p":420945,"sqm":30.7,"r":"2br","op":0},{"d":"2026-04-15","p":1050000,"sqm":79.3,"r":"2br","op":0},{"d":"2026-04-14","p":437938,"sqm":31.4,"r":"2br","op":0},{"d":"2026-04-02","p":120000,"sqm":10.3,"r":"1br","op":0},{"d":"2026-04-01","p":950400,"sqm":74.3,"r":"2br","op":0},{"d":"2026-03-26","p":460000,"sqm":34.3,"r":"2br","op":0},{"d":"2026-03-19","p":446000,"sqm":32.5,"r":"2br","op":0},{"d":"2026-03-17","p":428000,"sqm":31.7,"r":"2br","op":0},{"d":"2026-03-17","p":588000,"sqm":42.9,"r":"2br","op":0},{"d":"2026-03-17","p":468000,"sqm":34.3,"r":"2br","op":0},{"d":"2026-03-17","p":795760,"sqm":63.8,"r":"1br","op":0},{"d":"2026-03-10","p":1250379,"sqm":98.7,"r":"2br","op":0},{"d":"2026-03-09","p":442965,"sqm":33.7,"r":"2br","op":0},{"d":"2026-03-09","p":484000,"sqm":36.5,"r":"2br","op":0},{"d":"2026-03-06","p":1021668,"sqm":79.3,"r":"2br","op":0},{"d":"2026-03-04","p":810000,"sqm":63.7,"r":"1br","op":0},{"d":"2026-02-25","p":420945,"sqm":30.9,"r":"2br","op":0},{"d":"2026-02-24","p":430000,"sqm":33.4,"r":"studio","op":0},{"d":"2026-02-23","p":958368,"sqm":75.1,"r":"2br","op":0},{"d":"2026-02-17","p":745000,"sqm":62.5,"r":"1br","op":0},{"d":"2026-02-12","p":769728,"sqm":60.7,"r":"1br","op":0},{"d":"2026-02-09","p":810000,"sqm":62.5,"r":"1br","op":0},{"d":"2026-02-09","p":783144,"sqm":61.6,"r":"1br","op":0},{"d":"2026-02-06","p":199100,"sqm":12.2,"r":"studio","op":0},{"d":"2026-02-06","p":467493,"sqm":34.6,"r":"2br","op":0},{"d":"2026-02-06","p":370000,"sqm":24.6,"r":"1br","op":0},{"d":"2026-02-06","p":437614,"sqm":31.6,"r":"2br","op":0},{"d":"2026-02-05","p":812028,"sqm":64.7,"r":"1br","op":0},{"d":"2026-02-04","p":776196,"sqm":61.3,"r":"1br","op":0},{"d":"2026-02-04","p":776196,"sqm":61.1,"r":"1br","op":0},{"d":"2026-02-03","p":810000,"sqm":65.8,"r":"1br","op":0},{"d":"2026-02-02","p":371200,"sqm":25.1,"r":"1br","op":0},{"d":"2026-02-02","p":358187,"sqm":24.4,"r":"1br","op":0},{"d":"2026-01-27","p":792388,"sqm":61.8,"r":"1br","op":0},{"d":"2026-01-26","p":779728,"sqm":60.2,"r":"1br","op":0},{"d":"2026-01-26","p":1100000,"sqm":85.7,"r":"2br","op":0},{"d":"2026-01-23","p":958368,"sqm":74.7,"r":"2br","op":0},{"d":"2026-01-23","p":273000,"sqm":61.6,"r":"1br","op":0},{"d":"2026-01-23","p":358187,"sqm":25.0,"r":"1br","op":0},{"d":"2026-01-22","p":788668,"sqm":61.1,"r":"1br","op":0},{"d":"2026-01-15","p":540513,"sqm":42.5,"r":"2br","op":0},{"d":"2026-01-12","p":360000,"sqm":25.0,"r":"1br","op":0},{"d":"2026-01-08","p":920000,"sqm":75.3,"r":"2br","op":0},{"d":"2025-12-30","p":776196,"sqm":60.7,"r":"1br","op":0},{"d":"2025-12-30","p":730000,"sqm":61.6,"r":"1br","op":0},{"d":"2025-12-18","p":782388,"sqm":61.5,"r":"1br","op":0},{"d":"2025-12-18","p":352800,"sqm":24.9,"r":"1br","op":0},{"d":"2025-12-17","p":758000,"sqm":61.1,"r":"1br","op":0},{"d":"2025-12-17","p":1050000,"sqm":81.3,"r":"2br","op":0},{"d":"2025-12-16","p":345040,"sqm":25.1,"r":"1br","op":0},{"d":"2025-12-15","p":815028,"sqm":63.4,"r":"1br","op":0},{"d":"2025-12-15","p":338800,"sqm":23.2,"r":"1br","op":0},{"d":"2025-12-15","p":750000,"sqm":61.5,"r":"1br","op":0},{"d":"2025-11-27","p":800000,"sqm":65.3,"r":"1br","op":0},{"d":"2025-11-25","p":710000,"sqm":60.7,"r":"1br","op":0},{"d":"2025-11-21","p":600000,"sqm":51.3,"r":"1br","op":0},{"d":"2025-10-01","p":740000,"sqm":61.0,"r":"1br","op":0}]}