{"name":"C70","area":"Wadi Al Safa 7","proj":"","sn":8,"rn":0,"sy":[{"y":2011,"n":1,"rd":1,"ppsqm":13514,"price":2290000,"rd_ppsqm":13514},{"y":2012,"n":2,"rd":2,"ppsqm":5679,"price":945500,"rd_ppsqm":5679},{"y":2021,"n":1,"rd":1,"ppsqm":4815,"price":816000,"rd_ppsqm":4815},{"y":2024,"n":2,"rd":2,"ppsqm":7773,"price":1305242,"rd_ppsqm":7773},{"y":2025,"n":1,"rd":1,"ppsqm":12447,"price":2000000,"rd_ppsqm":12447},{"y":2026,"n":1,"rd":1,"ppsqm":10284,"price":1650000,"rd_ppsqm":10284}],"sr":{"2br":[{"y":2011,"n":1,"ppsqm":13514,"price":2290000,"rd_n":1,"rd_ppsqm":13514},{"y":2012,"n":2,"ppsqm":5679,"price":945500,"rd_n":2,"rd_ppsqm":5679},{"y":2021,"n":1,"ppsqm":4815,"price":816000,"rd_n":1,"rd_ppsqm":4815},{"y":2024,"n":2,"ppsqm":7773,"price":1305242,"rd_n":2,"rd_ppsqm":7773},{"y":2025,"n":1,"ppsqm":12447,"price":2000000,"rd_n":1,"rd_ppsqm":12447},{"y":2026,"n":1,"ppsqm":10284,"price":1650000,"rd_n":1,"rd_ppsqm":10284}]},"ry":[],"rr":{},"txs":[{"d":"2026-06-04","p":1650000,"sqm":160.5,"r":"2br","op":0},{"d":"2025-12-05","p":2000000,"sqm":160.7,"r":"2br","op":0},{"d":"2024-09-19","p":1275483,"sqm":169.5,"r":"2br","op":0},{"d":"2024-04-25","p":1335000,"sqm":166.5,"r":"2br","op":0},{"d":"2021-09-30","p":816000,"sqm":169.5,"r":"2br","op":0},{"d":"2012-11-28","p":955000,"sqm":166.5,"r":"2br","op":0},{"d":"2012-02-16","p":936000,"sqm":166.5,"r":"2br","op":0},{"d":"2011-07-14","p":2290000,"sqm":169.5,"r":"2br","op":0}]}